terrakio_core/__init__.py
terrakio_core/accessors.py
terrakio_core/async_client.py
terrakio_core/client.py
terrakio_core/config.py
terrakio_core/exceptions.py
terrakio_core/sync_client.py
terrakio_core/convenience_functions/create_dataset_file.py
terrakio_core/convenience_functions/geoquries.py
terrakio_core/convenience_functions/zonal_stats.py
terrakio_core/endpoints/auth.py
terrakio_core/endpoints/dataset_management.py
terrakio_core/endpoints/group_management.py
terrakio_core/endpoints/model_management.py
terrakio_core/endpoints/space_management.py
terrakio_core/endpoints/user_management.py
terrakio_core/endpoints/collections/__init__.py
terrakio_core/endpoints/collections/collections.py
terrakio_core/endpoints/collections/common.py
terrakio_core/endpoints/collections/data_operations.py
terrakio_core/endpoints/collections/generation.py
terrakio_core/endpoints/collections/ingestion.py
terrakio_core/endpoints/collections/tasks.py
terrakio_core/endpoints/collections/zonal_stats.py
terrakio_core/helper/bounded_taskgroup.py
terrakio_core/helper/decorators.py
terrakio_core/helper/tiles.py
terrakio_core-0.5.23.dist-info/METADATA
terrakio_core-0.5.23.dist-info/WHEEL
terrakio_core-0.5.23.dist-info/RECORD
