Metadata-Version: 2.4
Name: terrakio-core
Version: 0.5.23
Summary: Core package for the terrakio-python-api
Requires-Python: >=3.11
Requires-Dist: aiofiles>=24.1.0
Requires-Dist: aiohttp>=3.12.15
Requires-Dist: geopandas>=1.1.1
Requires-Dist: h5netcdf>=1.6.3
Requires-Dist: h5py>=3.14.0
Requires-Dist: nest-asyncio>=1.6.0
Requires-Dist: netcdf4>=1.7.2
Requires-Dist: onnxruntime>=1.23.2
Requires-Dist: psutil>=7.0.0
Requires-Dist: python-snappy>=0.7.3
Requires-Dist: rasterio>=1.4.3
Requires-Dist: scipy>=1.16.1
Requires-Dist: shapely>=2.1.1
Requires-Dist: typer>=0.19.2
Requires-Dist: xarray>=2025.7.1
Provides-Extra: ml
Requires-Dist: scikit-learn>=1.7.1; extra == 'ml'
Requires-Dist: skl2onnx>=1.19.1; extra == 'ml'
Requires-Dist: torch>=2.7.1; extra == 'ml'
